---- AspectJ Properties ---
AspectJ Compiler 1.9.6 built on Tuesday Jul 21, 2020 at 13:30:08 PDT
---- Dump Properties ---
Dump file: ajcore.20210502.135843.750.txt
Dump reason: org.aspectj.bridge.AbortException
Dump on exception: true
Dump at exit condition: abort
---- Exception Information ---
Message: abort trouble in: 
class org.springframework.boot.liquibase.LiquibaseChangelogMissingFailureAnalyzer extends org.springframework.boot.diagnostics.AbstractFailureAnalyzer:
  void <init>():
                    ALOAD_0     // Lorg/springframework/boot/liquibase/LiquibaseChangelogMissingFailureAnalyzer; this   (line 33)
                    INVOKESPECIAL org.springframework.boot.diagnostics.AbstractFailureAnalyzer.<init> ()V
    constructor-execution(void org.springframework.boot.liquibase.LiquibaseChangelogMissingFailureAnalyzer.<init>())
    |               RETURN
    constructor-execution(void org.springframework.boot.liquibase.LiquibaseChangelogMissingFailureAnalyzer.<init>())
  end void <init>()

  protected org.springframework.boot.diagnostics.FailureAnalysis analyze(Throwable, liquibase.exception.ChangeLogParseException):
                    ALOAD_0     // Lorg/springframework/boot/liquibase/LiquibaseChangelogMissingFailureAnalyzer; this   (line 37)
                    ALOAD_2     // Lliquibase/exception/ChangeLogParseException; cause
                    LDC java.io.FileNotFoundException
                    INVOKEVIRTUAL org.springframework.boot.liquibase.LiquibaseChangelogMissingFailureAnalyzer.findCause (Ljava/lang/Throwable;Ljava/lang/Class;)Ljava/lang/Throwable;
                    CHECKCAST java.io.FileNotFoundException
                    ASTORE_3
                    ALOAD_3     // Ljava/io/FileNotFoundException; fileNotFound   (line 38)
                    IFNULL L0
                    ALOAD_0     // Lorg/springframework/boot/liquibase/LiquibaseChangelogMissingFailureAnalyzer; this   (line 39)
                    ALOAD_2     // Lliquibase/exception/ChangeLogParseException; cause
                    INVOKESPECIAL org.springframework.boot.liquibase.LiquibaseChangelogMissingFailureAnalyzer.extractChangelogPath (Lliquibase/exception/ChangeLogParseException;)Ljava/lang/String;
                    ASTORE 4
                    ALOAD 4     // Ljava/lang/String; changelogPath   (line 40)
                    INVOKESTATIC org.springframework.util.StringUtils.hasText (Ljava/lang/String;)Z
                    IFEQ L0
                    NEW org.springframework.boot.diagnostics.FailureAnalysis   (line 41)
                    DUP
                    ALOAD_0     // Lorg/springframework/boot/liquibase/LiquibaseChangelogMissingFailureAnalyzer; this
                    ALOAD 4     // Ljava/lang/String; changelogPath
                    INVOKESPECIAL org.springframework.boot.liquibase.LiquibaseChangelogMissingFailureAnalyzer.getDescription (Ljava/lang/String;)Ljava/lang/String;
                    LDC "Make sure a Liquibase changelog is present at the configured path."
                    ALOAD_2     // Lliquibase/exception/ChangeLogParseException; cause
                    INVOKESPECIAL org.springframework.boot.diagnostics.FailureAnalysis.<init> (Ljava/lang/String;Ljava/lang/String;Ljava/lang/Throwable;)V
                    ARETURN
                L0: ACONST_NULL   (line 45)
                    ARETURN
  end protected org.springframework.boot.diagnostics.FailureAnalysis analyze(Throwable, liquibase.exception.ChangeLogParseException)

  private String extractChangelogPath(liquibase.exception.ChangeLogParseException):
                    ALOAD_1     // Lliquibase/exception/ChangeLogParseException; cause   (line 49)
                    INVOKEVIRTUAL liquibase.exception.ChangeLogParseException.getMessage ()Ljava/lang/String;
                    LDC "Error parsing "
                    INVOKEVIRTUAL java.lang.String.length ()I
                    INVOKEVIRTUAL java.lang.String.substring (I)Ljava/lang/String;
                    ARETURN
  end private String extractChangelogPath(liquibase.exception.ChangeLogParseException)

  private String getDescription(String):
                    NEW java.lang.StringBuilder   (line 53)
                    DUP
                    INVOKESPECIAL java.lang.StringBuilder.<init> ()V
                    LDC "Liquibase failed to start because no changelog could be found at '"
                    INVOKEVIRTUAL java.lang.StringBuilder.append (Ljava/lang/String;)Ljava/lang/StringBuilder;
                    ALOAD_1     // Ljava/lang/String; changelogPath
                    INVOKEVIRTUAL java.lang.StringBuilder.append (Ljava/lang/String;)Ljava/lang/StringBuilder;
                    LDC "'."
                    INVOKEVIRTUAL java.lang.StringBuilder.append (Ljava/lang/String;)Ljava/lang/StringBuilder;
                    INVOKEVIRTUAL java.lang.StringBuilder.toString ()Ljava/lang/String;
                    ARETURN
  end private String getDescription(String)

  protected volatile org.springframework.boot.diagnostics.FailureAnalysis analyze(Throwable, Throwable):
                    ALOAD_0     // Lorg/springframework/boot/liquibase/LiquibaseChangelogMissingFailureAnalyzer; this   (line 33)
                    ALOAD_1
                    ALOAD_2
                    CHECKCAST liquibase.exception.ChangeLogParseException
                    INVOKEVIRTUAL org.springframework.boot.liquibase.LiquibaseChangelogMissingFailureAnalyzer.analyze (Ljava/lang/Throwable;Lliquibase/exception/ChangeLogParseException;)Lorg/springframework/boot/diagnostics/FailureAnalysis;
                    ARETURN
  end protected volatile org.springframework.boot.diagnostics.FailureAnalysis analyze(Throwable, Throwable)

end class org.springframework.boot.liquibase.LiquibaseChangelogMissingFailureAnalyzer
 -- (NullPointerException) Cannot invoke "org.aspectj.weaver.ResolvedMember.matches(org.aspectj.weaver.ResolvedMember, boolean)" because "candidate" is null
Cannot invoke "org.aspectj.weaver.ResolvedMember.matches(org.aspectj.weaver.ResolvedMember, boolean)" because "candidate" is null
java.lang.NullPointerException: Cannot invoke "org.aspectj.weaver.ResolvedMember.matches(org.aspectj.weaver.ResolvedMember, boolean)" because "candidate" is null
	at org.aspectj.weaver.ResolvedType.lookupResolvedMember(ResolvedType.java:650)
	at org.aspectj.weaver.JoinPointSignatureIterator.findSignaturesFromSupertypes(JoinPointSignatureIterator.java:192)
	at org.aspectj.weaver.JoinPointSignatureIterator.hasNext(JoinPointSignatureIterator.java:68)
	at org.aspectj.weaver.patterns.SignaturePattern.matches(SignaturePattern.java:320)
	at org.aspectj.weaver.patterns.KindedPointcut.matchInternal(KindedPointcut.java:202)
	at org.aspectj.weaver.patterns.Pointcut.match(Pointcut.java:137)
	at org.aspectj.weaver.patterns.AndPointcut.matchInternal(AndPointcut.java:56)
	at org.aspectj.weaver.patterns.Pointcut.match(Pointcut.java:137)
	at org.aspectj.weaver.patterns.OrPointcut.matchInternal(OrPointcut.java:60)
	at org.aspectj.weaver.patterns.Pointcut.match(Pointcut.java:137)
	at org.aspectj.weaver.ShadowMunger.match(ShadowMunger.java:113)
	at org.aspectj.weaver.Advice.match(Advice.java:113)
	at org.aspectj.weaver.bcel.BcelAdvice.match(BcelAdvice.java:161)
	at org.aspectj.weaver.bcel.BcelClassWeaver.match(BcelClassWeaver.java:3328)
	at org.aspectj.weaver.bcel.BcelClassWeaver.match(BcelClassWeaver.java:2704)
	at org.aspectj.weaver.bcel.BcelClassWeaver.weave(BcelClassWeaver.java:483)
	at org.aspectj.weaver.bcel.BcelClassWeaver.weave(BcelClassWeaver.java:103)
	at org.aspectj.weaver.bcel.BcelWeaver.weave(BcelWeaver.java:1712)
	at org.aspectj.weaver.bcel.BcelWeaver.weaveWithoutDump(BcelWeaver.java:1656)
	at org.aspectj.weaver.bcel.BcelWeaver.weaveAndNotify(BcelWeaver.java:1421)
	at org.aspectj.weaver.bcel.BcelWeaver.weave(BcelWeaver.java:1195)
	at org.aspectj.weaver.tools.WeavingAdaptor.getWovenBytes(WeavingAdaptor.java:551)
	at org.aspectj.weaver.tools.WeavingAdaptor.weaveClass(WeavingAdaptor.java:387)
	at org.aspectj.weaver.loadtime.Aj.preProcess(Aj.java:116)
	at org.aspectj.weaver.loadtime.ClassPreProcessorAgentAdapter.transform(ClassPreProcessorAgentAdapter.java:51)
	at java.instrument/java.lang.instrument.ClassFileTransformer.transform(ClassFileTransformer.java:246)
	at java.instrument/sun.instrument.TransformerManager.transform(TransformerManager.java:188)
	at java.instrument/sun.instrument.InstrumentationImpl.transform(InstrumentationImpl.java:563)
	at java.base/java.lang.ClassLoader.defineClass1(Native Method)
	at java.base/java.lang.ClassLoader.defineClass(ClassLoader.java:1016)
	at java.base/java.security.SecureClassLoader.defineClass(SecureClassLoader.java:151)
	at java.base/jdk.internal.loader.BuiltinClassLoader.defineClass(BuiltinClassLoader.java:825)
	at java.base/jdk.internal.loader.BuiltinClassLoader.findClassOnClassPathOrNull(BuiltinClassLoader.java:723)
	at java.base/jdk.internal.loader.BuiltinClassLoader.loadClassOrNull(BuiltinClassLoader.java:646)
	at java.base/jdk.internal.loader.BuiltinClassLoader.loadClass(BuiltinClassLoader.java:604)
	at java.base/jdk.internal.loader.ClassLoaders$AppClassLoader.loadClass(ClassLoaders.java:168)
	at java.base/java.lang.ClassLoader.loadClass(ClassLoader.java:522)
	at java.base/java.lang.Class.forName0(Native Method)
	at java.base/java.lang.Class.forName(Class.java:468)
	at org.springframework.util.ClassUtils.forName(ClassUtils.java:284)
	at org.springframework.boot.diagnostics.FailureAnalyzers.createAnalyzer(FailureAnalyzers.java:91)
	at org.springframework.boot.diagnostics.FailureAnalyzers.loadFailureAnalyzers(FailureAnalyzers.java:77)
	at org.springframework.boot.diagnostics.FailureAnalyzers.<init>(FailureAnalyzers.java:64)
	at org.springframework.boot.diagnostics.FailureAnalyzers.<init>(FailureAnalyzers.java:59)
	at java.base/jdk.internal.reflect.NativeConstructorAccessorImpl.newInstance0(Native Method)
	at java.base/jdk.internal.reflect.NativeConstructorAccessorImpl.newInstance(NativeConstructorAccessorImpl.java:64)
	at java.base/jdk.internal.reflect.DelegatingConstructorAccessorImpl.newInstance(DelegatingConstructorAccessorImpl.java:45)
	at java.base/java.lang.reflect.Constructor.newInstanceWithCaller(Constructor.java:500)
	at java.base/java.lang.reflect.Constructor.newInstance(Constructor.java:481)
	at org.springframework.beans.BeanUtils.instantiateClass(BeanUtils.java:212)
	at org.springframework.boot.SpringApplication.createSpringFactoriesInstances(SpringApplication.java:463)
	at org.springframework.boot.SpringApplication.getSpringFactoriesInstances(SpringApplication.java:449)
	at org.springframework.boot.SpringApplication.getExceptionReporters(SpringApplication.java:835)
	at org.springframework.boot.SpringApplication.handleRunFailure(SpringApplication.java:821)
	at org.springframework.boot.SpringApplication.run(SpringApplication.java:336)
	at io.swagger.Swagger2SpringBoot.main(Swagger2SpringBoot.java:26)

org.aspectj.bridge.AbortException: trouble in: 
class org.springframework.boot.liquibase.LiquibaseChangelogMissingFailureAnalyzer extends org.springframework.boot.diagnostics.AbstractFailureAnalyzer:
  void <init>():
                    ALOAD_0     // Lorg/springframework/boot/liquibase/LiquibaseChangelogMissingFailureAnalyzer; this   (line 33)
                    INVOKESPECIAL org.springframework.boot.diagnostics.AbstractFailureAnalyzer.<init> ()V
    constructor-execution(void org.springframework.boot.liquibase.LiquibaseChangelogMissingFailureAnalyzer.<init>())
    |               RETURN
    constructor-execution(void org.springframework.boot.liquibase.LiquibaseChangelogMissingFailureAnalyzer.<init>())
  end void <init>()

  protected org.springframework.boot.diagnostics.FailureAnalysis analyze(Throwable, liquibase.exception.ChangeLogParseException):
                    ALOAD_0     // Lorg/springframework/boot/liquibase/LiquibaseChangelogMissingFailureAnalyzer; this   (line 37)
                    ALOAD_2     // Lliquibase/exception/ChangeLogParseException; cause
                    LDC java.io.FileNotFoundException
                    INVOKEVIRTUAL org.springframework.boot.liquibase.LiquibaseChangelogMissingFailureAnalyzer.findCause (Ljava/lang/Throwable;Ljava/lang/Class;)Ljava/lang/Throwable;
                    CHECKCAST java.io.FileNotFoundException
                    ASTORE_3
                    ALOAD_3     // Ljava/io/FileNotFoundException; fileNotFound   (line 38)
                    IFNULL L0
                    ALOAD_0     // Lorg/springframework/boot/liquibase/LiquibaseChangelogMissingFailureAnalyzer; this   (line 39)
                    ALOAD_2     // Lliquibase/exception/ChangeLogParseException; cause
                    INVOKESPECIAL org.springframework.boot.liquibase.LiquibaseChangelogMissingFailureAnalyzer.extractChangelogPath (Lliquibase/exception/ChangeLogParseException;)Ljava/lang/String;
                    ASTORE 4
                    ALOAD 4     // Ljava/lang/String; changelogPath   (line 40)
                    INVOKESTATIC org.springframework.util.StringUtils.hasText (Ljava/lang/String;)Z
                    IFEQ L0
                    NEW org.springframework.boot.diagnostics.FailureAnalysis   (line 41)
                    DUP
                    ALOAD_0     // Lorg/springframework/boot/liquibase/LiquibaseChangelogMissingFailureAnalyzer; this
                    ALOAD 4     // Ljava/lang/String; changelogPath
                    INVOKESPECIAL org.springframework.boot.liquibase.LiquibaseChangelogMissingFailureAnalyzer.getDescription (Ljava/lang/String;)Ljava/lang/String;
                    LDC "Make sure a Liquibase changelog is present at the configured path."
                    ALOAD_2     // Lliquibase/exception/ChangeLogParseException; cause
                    INVOKESPECIAL org.springframework.boot.diagnostics.FailureAnalysis.<init> (Ljava/lang/String;Ljava/lang/String;Ljava/lang/Throwable;)V
                    ARETURN
                L0: ACONST_NULL   (line 45)
                    ARETURN
  end protected org.springframework.boot.diagnostics.FailureAnalysis analyze(Throwable, liquibase.exception.ChangeLogParseException)

  private String extractChangelogPath(liquibase.exception.ChangeLogParseException):
                    ALOAD_1     // Lliquibase/exception/ChangeLogParseException; cause   (line 49)
                    INVOKEVIRTUAL liquibase.exception.ChangeLogParseException.getMessage ()Ljava/lang/String;
                    LDC "Error parsing "
                    INVOKEVIRTUAL java.lang.String.length ()I
                    INVOKEVIRTUAL java.lang.String.substring (I)Ljava/lang/String;
                    ARETURN
  end private String extractChangelogPath(liquibase.exception.ChangeLogParseException)

  private String getDescription(String):
                    NEW java.lang.StringBuilder   (line 53)
                    DUP
                    INVOKESPECIAL java.lang.StringBuilder.<init> ()V
                    LDC "Liquibase failed to start because no changelog could be found at '"
                    INVOKEVIRTUAL java.lang.StringBuilder.append (Ljava/lang/String;)Ljava/lang/StringBuilder;
                    ALOAD_1     // Ljava/lang/String; changelogPath
                    INVOKEVIRTUAL java.lang.StringBuilder.append (Ljava/lang/String;)Ljava/lang/StringBuilder;
                    LDC "'."
                    INVOKEVIRTUAL java.lang.StringBuilder.append (Ljava/lang/String;)Ljava/lang/StringBuilder;
                    INVOKEVIRTUAL java.lang.StringBuilder.toString ()Ljava/lang/String;
                    ARETURN
  end private String getDescription(String)

  protected volatile org.springframework.boot.diagnostics.FailureAnalysis analyze(Throwable, Throwable):
                    ALOAD_0     // Lorg/springframework/boot/liquibase/LiquibaseChangelogMissingFailureAnalyzer; this   (line 33)
                    ALOAD_1
                    ALOAD_2
                    CHECKCAST liquibase.exception.ChangeLogParseException
                    INVOKEVIRTUAL org.springframework.boot.liquibase.LiquibaseChangelogMissingFailureAnalyzer.analyze (Ljava/lang/Throwable;Lliquibase/exception/ChangeLogParseException;)Lorg/springframework/boot/diagnostics/FailureAnalysis;
                    ARETURN
  end protected volatile org.springframework.boot.diagnostics.FailureAnalysis analyze(Throwable, Throwable)

end class org.springframework.boot.liquibase.LiquibaseChangelogMissingFailureAnalyzer

	at org.aspectj.bridge.MessageWriter.handleMessage(MessageWriter.java:47)
	at org.aspectj.weaver.tools.WeavingAdaptor$WeavingAdaptorMessageWriter.handleMessage(WeavingAdaptor.java:821)
	at org.aspectj.weaver.tools.WeavingAdaptor$WeavingAdaptorMessageHolder.handleMessage(WeavingAdaptor.java:766)
	at org.aspectj.weaver.bcel.BcelWeaver.weave(BcelWeaver.java:1738)
	at org.aspectj.weaver.bcel.BcelWeaver.weaveWithoutDump(BcelWeaver.java:1656)
	at org.aspectj.weaver.bcel.BcelWeaver.weaveAndNotify(BcelWeaver.java:1421)
	at org.aspectj.weaver.bcel.BcelWeaver.weave(BcelWeaver.java:1195)
	at org.aspectj.weaver.tools.WeavingAdaptor.getWovenBytes(WeavingAdaptor.java:551)
	at org.aspectj.weaver.tools.WeavingAdaptor.weaveClass(WeavingAdaptor.java:387)
	at org.aspectj.weaver.loadtime.Aj.preProcess(Aj.java:116)
	at org.aspectj.weaver.loadtime.ClassPreProcessorAgentAdapter.transform(ClassPreProcessorAgentAdapter.java:51)
	at java.instrument/java.lang.instrument.ClassFileTransformer.transform(ClassFileTransformer.java:246)
	at java.instrument/sun.instrument.TransformerManager.transform(TransformerManager.java:188)
	at java.instrument/sun.instrument.InstrumentationImpl.transform(InstrumentationImpl.java:563)
	at java.base/java.lang.ClassLoader.defineClass1(Native Method)
	at java.base/java.lang.ClassLoader.defineClass(ClassLoader.java:1016)
	at java.base/java.security.SecureClassLoader.defineClass(SecureClassLoader.java:151)
	at java.base/jdk.internal.loader.BuiltinClassLoader.defineClass(BuiltinClassLoader.java:825)
	at java.base/jdk.internal.loader.BuiltinClassLoader.findClassOnClassPathOrNull(BuiltinClassLoader.java:723)
	at java.base/jdk.internal.loader.BuiltinClassLoader.loadClassOrNull(BuiltinClassLoader.java:646)
	at java.base/jdk.internal.loader.BuiltinClassLoader.loadClass(BuiltinClassLoader.java:604)
	at java.base/jdk.internal.loader.ClassLoaders$AppClassLoader.loadClass(ClassLoaders.java:168)
	at java.base/java.lang.ClassLoader.loadClass(ClassLoader.java:522)
	at java.base/java.lang.Class.forName0(Native Method)
	at java.base/java.lang.Class.forName(Class.java:468)
	at org.springframework.util.ClassUtils.forName(ClassUtils.java:284)
	at org.springframework.boot.diagnostics.FailureAnalyzers.createAnalyzer(FailureAnalyzers.java:91)
	at org.springframework.boot.diagnostics.FailureAnalyzers.loadFailureAnalyzers(FailureAnalyzers.java:77)
	at org.springframework.boot.diagnostics.FailureAnalyzers.<init>(FailureAnalyzers.java:64)
	at org.springframework.boot.diagnostics.FailureAnalyzers.<init>(FailureAnalyzers.java:59)
	at java.base/jdk.internal.reflect.NativeConstructorAccessorImpl.newInstance0(Native Method)
	at java.base/jdk.internal.reflect.NativeConstructorAccessorImpl.newInstance(NativeConstructorAccessorImpl.java:64)
	at java.base/jdk.internal.reflect.DelegatingConstructorAccessorImpl.newInstance(DelegatingConstructorAccessorImpl.java:45)
	at java.base/java.lang.reflect.Constructor.newInstanceWithCaller(Constructor.java:500)
	at java.base/java.lang.reflect.Constructor.newInstance(Constructor.java:481)
	at org.springframework.beans.BeanUtils.instantiateClass(BeanUtils.java:212)
	at org.springframework.boot.SpringApplication.createSpringFactoriesInstances(SpringApplication.java:463)
	at org.springframework.boot.SpringApplication.getSpringFactoriesInstances(SpringApplication.java:449)
	at org.springframework.boot.SpringApplication.getExceptionReporters(SpringApplication.java:835)
	at org.springframework.boot.SpringApplication.handleRunFailure(SpringApplication.java:821)
	at org.springframework.boot.SpringApplication.run(SpringApplication.java:336)
	at io.swagger.Swagger2SpringBoot.main(Swagger2SpringBoot.java:26)
---- System Properties ---
java.specification.version=15
sun.cpu.isalist=amd64
sun.jnu.encoding=Cp1250
java.class.path=D:\REPO\ISM\target\classes;C:\Users\pietr\.m2\repository\org\javassist\javassist\3.23.1-GA\javassist-3.23.1-GA.jar;C:\Users\pietr\.m2\repository\org\springframework\boot\spring-boot-starter-web\2.4.0\spring-boot-starter-web-2.4.0.jar;C:\Users\pietr\.m2\repository\org\springframework\boot\spring-boot-starter\2.4.0\spring-boot-starter-2.4.0.jar;C:\Users\pietr\.m2\repository\org\springframework\boot\spring-boot\2.4.0\spring-boot-2.4.0.jar;C:\Users\pietr\.m2\repository\org\springframework\boot\spring-boot-autoconfigure\2.4.0\spring-boot-autoconfigure-2.4.0.jar;C:\Users\pietr\.m2\repository\org\springframework\boot\spring-boot-starter-logging\2.4.0\spring-boot-starter-logging-2.4.0.jar;C:\Users\pietr\.m2\repository\ch\qos\logback\logback-classic\1.2.3\logback-classic-1.2.3.jar;C:\Users\pietr\.m2\repository\ch\qos\logback\logback-core\1.2.3\logback-core-1.2.3.jar;C:\Users\pietr\.m2\repository\org\apache\logging\log4j\log4j-to-slf4j\2.13.3\log4j-to-slf4j-2.13.3.jar;C:\Users\pietr\.m2\repository\org\apache\logging\log4j\log4j-api\2.13.3\log4j-api-2.13.3.jar;C:\Users\pietr\.m2\repository\org\slf4j\jul-to-slf4j\1.7.30\jul-to-slf4j-1.7.30.jar;C:\Users\pietr\.m2\repository\org\yaml\snakeyaml\1.27\snakeyaml-1.27.jar;C:\Users\pietr\.m2\repository\org\springframework\boot\spring-boot-starter-json\2.4.0\spring-boot-starter-json-2.4.0.jar;C:\Users\pietr\.m2\repository\com\fasterxml\jackson\datatype\jackson-datatype-jdk8\2.11.3\jackson-datatype-jdk8-2.11.3.jar;C:\Users\pietr\.m2\repository\com\fasterxml\jackson\datatype\jackson-datatype-jsr310\2.11.3\jackson-datatype-jsr310-2.11.3.jar;C:\Users\pietr\.m2\repository\com\fasterxml\jackson\module\jackson-module-parameter-names\2.11.3\jackson-module-parameter-names-2.11.3.jar;C:\Users\pietr\.m2\repository\org\springframework\spring-web\5.3.1\spring-web-5.3.1.jar;C:\Users\pietr\.m2\repository\org\springframework\spring-webmvc\5.3.1\spring-webmvc-5.3.1.jar;C:\Users\pietr\.m2\repository\org\springframework\spring-expression\5.3.1\spring-expression-5.3.1.jar;C:\Users\pietr\.m2\repository\org\springframework\boot\spring-boot-starter-tomcat\2.4.0\spring-boot-starter-tomcat-2.4.0.jar;C:\Users\pietr\.m2\repository\jakarta\annotation\jakarta.annotation-api\1.3.5\jakarta.annotation-api-1.3.5.jar;C:\Users\pietr\.m2\repository\org\apache\tomcat\embed\tomcat-embed-core\9.0.39\tomcat-embed-core-9.0.39.jar;C:\Users\pietr\.m2\repository\org\glassfish\jakarta.el\3.0.3\jakarta.el-3.0.3.jar;C:\Users\pietr\.m2\repository\org\apache\tomcat\embed\tomcat-embed-websocket\9.0.39\tomcat-embed-websocket-9.0.39.jar;C:\Users\pietr\.m2\repository\io\springfox\springfox-oas\3.0.0\springfox-oas-3.0.0.jar;C:\Users\pietr\.m2\repository\io\swagger\core\v3\swagger-annotations\2.1.2\swagger-annotations-2.1.2.jar;C:\Users\pietr\.m2\repository\io\swagger\core\v3\swagger-models\2.1.2\swagger-models-2.1.2.jar;C:\Users\pietr\.m2\repository\com\fasterxml\jackson\core\jackson-annotations\2.11.3\jackson-annotations-2.11.3.jar;C:\Users\pietr\.m2\repository\io\springfox\springfox-spi\3.0.0\springfox-spi-3.0.0.jar;C:\Users\pietr\.m2\repository\io\springfox\springfox-schema\3.0.0\springfox-schema-3.0.0.jar;C:\Users\pietr\.m2\repository\io\springfox\springfox-core\3.0.0\springfox-core-3.0.0.jar;C:\Users\pietr\.m2\repository\net\bytebuddy\byte-buddy\1.10.18\byte-buddy-1.10.18.jar;C:\Users\pietr\.m2\repository\io\springfox\springfox-spring-web\3.0.0\springfox-spring-web-3.0.0.jar;C:\Users\pietr\.m2\repository\io\github\classgraph\classgraph\4.8.83\classgraph-4.8.83.jar;C:\Users\pietr\.m2\repository\io\springfox\springfox-spring-webmvc\3.0.0\springfox-spring-webmvc-3.0.0.jar;C:\Users\pietr\.m2\repository\io\springfox\springfox-spring-webflux\3.0.0\springfox-spring-webflux-3.0.0.jar;C:\Users\pietr\.m2\repository\io\springfox\springfox-swagger-common\3.0.0\springfox-swagger-common-3.0.0.jar;C:\Users\pietr\.m2\repository\io\swagger\swagger-annotations\1.5.20\swagger-annotations-1.5.20.jar;C:\Users\pietr\.m2\repository\io\swagger\swagger-models\1.5.20\swagger-models-1.5.20.jar;C:\Users\pietr\.m2\repository\com\fasterxml\classmate\1.5.1\classmate-1.5.1.jar;C:\Users\pietr\.m2\repository\org\slf4j\slf4j-api\1.7.30\slf4j-api-1.7.30.jar;C:\Users\pietr\.m2\repository\org\springframework\plugin\spring-plugin-metadata\2.0.0.RELEASE\spring-plugin-metadata-2.0.0.RELEASE.jar;C:\Users\pietr\.m2\repository\org\mapstruct\mapstruct\1.3.1.Final\mapstruct-1.3.1.Final.jar;C:\Users\pietr\.m2\repository\io\springfox\springfox-swagger-ui\3.0.0\springfox-swagger-ui-3.0.0.jar;C:\Users\pietr\.m2\repository\com\github\joschi\jackson\jackson-datatype-threetenbp\2.6.4\jackson-datatype-threetenbp-2.6.4.jar;C:\Users\pietr\.m2\repository\org\threeten\threetenbp\1.3.1\threetenbp-1.3.1.jar;C:\Users\pietr\.m2\repository\com\fasterxml\jackson\core\jackson-core\2.11.3\jackson-core-2.11.3.jar;C:\Users\pietr\.m2\repository\com\fasterxml\jackson\core\jackson-databind\2.11.3\jackson-databind-2.11.3.jar;C:\Users\pietr\.m2\repository\javax\xml\bind\jaxb-api\2.3.1\jaxb-api-2.3.1.jar;C:\Users\pietr\.m2\repository\javax\activation\javax.activation-api\1.2.0\javax.activation-api-1.2.0.jar;C:\Users\pietr\.m2\repository\javax\activation\activation\1.1\activation-1.1.jar;C:\Users\pietr\.m2\repository\org\glassfish\jaxb\jaxb-runtime\2.3.3\jaxb-runtime-2.3.3.jar;C:\Users\pietr\.m2\repository\jakarta\xml\bind\jakarta.xml.bind-api\2.3.3\jakarta.xml.bind-api-2.3.3.jar;C:\Users\pietr\.m2\repository\org\glassfish\jaxb\txw2\2.3.3\txw2-2.3.3.jar;C:\Users\pietr\.m2\repository\com\sun\istack\istack-commons-runtime\3.0.11\istack-commons-runtime-3.0.11.jar;C:\Users\pietr\.m2\repository\com\sun\activation\jakarta.activation\1.2.2\jakarta.activation-1.2.2.jar;C:\Users\pietr\.m2\repository\javax\validation\validation-api\2.0.1.Final\validation-api-2.0.1.Final.jar;C:\Users\pietr\.m2\repository\org\springframework\plugin\spring-plugin-core\2.0.0.RELEASE\spring-plugin-core-2.0.0.RELEASE.jar;C:\Users\pietr\.m2\repository\org\springframework\spring-beans\5.3.1\spring-beans-5.3.1.jar;C:\Users\pietr\.m2\repository\org\springframework\spring-context\5.3.1\spring-context-5.3.1.jar;C:\Users\pietr\.m2\repository\org\springframework\spring-aop\5.3.1\spring-aop-5.3.1.jar;C:\Users\pietr\.m2\repository\org\springframework\boot\spring-boot-starter-data-jpa\2.4.0\spring-boot-starter-data-jpa-2.4.0.jar;C:\Users\pietr\.m2\repository\org\springframework\boot\spring-boot-starter-jdbc\2.4.0\spring-boot-starter-jdbc-2.4.0.jar;C:\Users\pietr\.m2\repository\com\zaxxer\HikariCP\3.4.5\HikariCP-3.4.5.jar;C:\Users\pietr\.m2\repository\org\springframework\spring-jdbc\5.3.1\spring-jdbc-5.3.1.jar;C:\Users\pietr\.m2\repository\jakarta\transaction\jakarta.transaction-api\1.3.3\jakarta.transaction-api-1.3.3.jar;C:\Users\pietr\.m2\repository\jakarta\persistence\jakarta.persistence-api\2.2.3\jakarta.persistence-api-2.2.3.jar;C:\Users\pietr\.m2\repository\org\hibernate\hibernate-core\5.2.10.Final\hibernate-core-5.2.10.Final.jar;C:\Users\pietr\.m2\repository\org\hibernate\javax\persistence\hibernate-jpa-2.1-api\1.0.0.Final\hibernate-jpa-2.1-api-1.0.0.Final.jar;C:\Users\pietr\.m2\repository\antlr\antlr\2.7.7\antlr-2.7.7.jar;C:\Users\pietr\.m2\repository\org\jboss\jandex\2.0.3.Final\jandex-2.0.3.Final.jar;C:\Users\pietr\.m2\repository\dom4j\dom4j\1.6.1\dom4j-1.6.1.jar;C:\Users\pietr\.m2\repository\org\hibernate\common\hibernate-commons-annotations\5.0.1.Final\hibernate-commons-annotations-5.0.1.Final.jar;C:\Users\pietr\.m2\repository\org\springframework\spring-aspects\5.3.1\spring-aspects-5.3.1.jar;C:\Users\pietr\.m2\repository\org\springframework\boot\spring-boot-starter-data-rest\2.4.0\spring-boot-starter-data-rest-2.4.0.jar;C:\Users\pietr\.m2\repository\org\springframework\data\spring-data-rest-webmvc\3.4.1\spring-data-rest-webmvc-3.4.1.jar;C:\Users\pietr\.m2\repository\org\springframework\data\spring-data-rest-core\3.4.1\spring-data-rest-core-3.4.1.jar;C:\Users\pietr\.m2\repository\org\springframework\hateoas\spring-hateoas\1.2.1\spring-hateoas-1.2.1.jar;C:\Users\pietr\.m2\repository\org\atteo\evo-inflector\1.2.2\evo-inflector-1.2.2.jar;C:\Users\pietr\.m2\repository\org\springframework\data\spring-data-jpa\2.4.1\spring-data-jpa-2.4.1.jar;C:\Users\pietr\.m2\repository\org\springframework\spring-orm\5.3.1\spring-orm-5.3.1.jar;C:\Users\pietr\.m2\repository\org\springframework\spring-tx\5.3.1\spring-tx-5.3.1.jar;C:\Users\pietr\.m2\repository\org\springframework\spring-core\5.3.1\spring-core-5.3.1.jar;C:\Users\pietr\.m2\repository\org\springframework\spring-jcl\5.3.1\spring-jcl-5.3.1.jar;C:\Users\pietr\.m2\repository\org\springframework\data\spring-data-commons\2.4.1\spring-data-commons-2.4.1.jar;C:\Users\pietr\.m2\repository\org\hibernate\hibernate-envers\5.2.10.Final\hibernate-envers-5.2.10.Final.jar;C:\Users\pietr\.m2\repository\org\jboss\logging\jboss-logging\3.4.1.Final\jboss-logging-3.4.1.Final.jar;C:\Users\pietr\.m2\repository\com\github\gwenn\sqlite-dialect\master\sqlite-dialect-master.jar;C:\Users\pietr\.m2\repository\org\xerial\sqlite-jdbc\3.32.3.2\sqlite-jdbc-3.32.3.2.jar;C:\Users\pietr\.m2\repository\net\sf\ehcache\ehcache\2.10.6\ehcache-2.10.6.jar;C:\Users\pietr\.m2\repository\org\springframework\boot\spring-boot-starter-aop\2.4.0\spring-boot-starter-aop-2.4.0.jar;C:\Users\pietr\.m2\repository\org\aspectj\aspectjrt\1.9.6\aspectjrt-1.9.6.jar;C:\Users\pietr\.m2\repository\org\aspectj\aspectjweaver\1.9.6\aspectjweaver-1.9.6.jar;C:\Users\pietr\.m2\repository\org\springframework\spring-instrument\5.3.1\spring-instrument-5.3.1.jar;C:\Users\pietr\.m2\repository\com\jayway\jsonpath\json-path\2.4.0\json-path-2.4.0.jar;C:\Users\pietr\.m2\repository\net\minidev\json-smart\2.3\json-smart-2.3.jar;C:\Users\pietr\.m2\repository\net\minidev\accessors-smart\1.2\accessors-smart-1.2.jar;C:\Users\pietr\.m2\repository\org\ow2\asm\asm\5.0.4\asm-5.0.4.jar
com.sun.management.jmxremote.authenticate=false
java.vm.vendor=Oracle Corporation
sun.arch.data.model=64
user.variant=
java.vendor.url=https://java.oracle.com/
catalina.useNaming=false
user.timezone=Europe/Warsaw
user.country.format=PL
java.vm.specification.version=15
os.name=Windows 10
sun.java.launcher=SUN_STANDARD
user.country=GB
sun.boot.library.path=C:\Users\pietr\Downloads\sts-4.10.0.RELEASE\plugins\org.eclipse.justj.openjdk.hotspot.jre.full.win32.x86_64_15.0.2.v20210201-0955\jre\bin
com.sun.management.jmxremote.ssl=false
spring.application.admin.enabled=true
sun.java.command=io.swagger.Swagger2SpringBoot --spring.output.ansi.enabled=always
com.sun.management.jmxremote=
jdk.debug=release
sun.cpu.endian=little
spring.boot.project.name=backyard-app
user.home=C:\Users\pietr
user.language=en
java.specification.vendor=Oracle Corporation
java.version.date=2021-01-19
java.home=C:\Users\pietr\Downloads\sts-4.10.0.RELEASE\plugins\org.eclipse.justj.openjdk.hotspot.jre.full.win32.x86_64_15.0.2.v20210201-0955\jre
file.separator=\
java.vm.compressedOopsMode=32-bit
line.separator=

java.vm.specification.vendor=Oracle Corporation
java.specification.name=Java Platform API Specification
FILE_LOG_CHARSET=UTF-8
java.awt.headless=true
user.script=
sun.management.compiler=HotSpot 64-Bit Tiered Compilers
java.runtime.version=15.0.2+7-27
user.name=pietr
spring.jmx.enabled=true
path.separator=;
os.version=10.0
java.runtime.name=OpenJDK Runtime Environment
file.encoding=UTF-8
spring.beaninfo.ignore=true
java.vm.name=OpenJDK 64-Bit Server VM
java.vendor.url.bug=https://bugreport.java.com/bugreport/
java.io.tmpdir=C:\Users\pietr\AppData\Local\Temp\
catalina.home=C:\Users\pietr\AppData\Local\Temp\tomcat.8080.1050718551460589346
com.zaxxer.hikari.pool_number=1
com.sun.management.jmxremote.port=64244
java.version=15.0.2
user.dir=D:\REPO\ISM
os.arch=amd64
java.vm.specification.name=Java Virtual Machine Specification
PID=8268
user.language.format=pl
sun.os.patch.level=
CONSOLE_LOG_CHARSET=UTF-8
catalina.base=C:\Users\pietr\AppData\Local\Temp\tomcat.8080.1050718551460589346
java.library.path=C:\Users\pietr\Downloads\sts-4.10.0.RELEASE\plugins\org.eclipse.justj.openjdk.hotspot.jre.full.win32.x86_64_15.0.2.v20210201-0955\jre\bin;C:\Windows\Sun\Java\bin;C:\Windows\system32;C:\Windows;C:/Users/pietr/Downloads/sts-4.10.0.RELEASE//plugins/org.eclipse.justj.openjdk.hotspot.jre.full.win32.x86_64_15.0.2.v20210201-0955/jre/bin/server;C:/Users/pietr/Downloads/sts-4.10.0.RELEASE//plugins/org.eclipse.justj.openjdk.hotspot.jre.full.win32.x86_64_15.0.2.v20210201-0955/jre/bin;C:\Program Files\Common Files\Oracle\Java\javapath;C:\Windows\system32;C:\Windows;C:\Windows\System32\Wbem;C:\Windows\System32\WindowsPowerShell\v1.0\;C:\Windows\System32\OpenSSH\;C:\Program Files\dotnet\;C:\Program Files\Microsoft SQL Server\130\Tools\Binn\;C:\Program Files\Microsoft SQL Server\Client SDK\ODBC\170\Tools\Binn\;C:\Program Files (x86)\Microsoft SQL Server\150\Tools\Binn\;C:\Program Files\Microsoft SQL Server\150\Tools\Binn\;C:\Program Files\Microsoft SQL Server\150\DTS\Binn\;C:\Program Files (x86)\Microsoft SQL Server\150\DTS\Binn\;C:\Program Files\Azure Data Studio\bin;C:\Program Files\Git\cmd;C:\Program Files\nodejs\;C:\Program Files (x86)\Calibre2\;C:\Users\pietr\AppData\Local\Programs\Python\Python39\Scripts\;C:\Users\pietr\AppData\Local\Programs\Python\Python39\;C:\Users\pietr\AppData\Local\Microsoft\WindowsApps;C:\Users\pietr\.dotnet\tools;C:\Users\pietr\AppData\Local\Programs\Microsoft VS Code\bin;C:\Program Files\Azure Data Studio\bin;C:\Users\pietr\AppData\Roaming\npm;C:\Users\pietr\Downloads\sts-4.10.0.RELEASE;;.
java.vm.info=mixed mode
java.vendor=Oracle Corporation
java.vm.version=15.0.2+7-27
java.rmi.server.hostname=localhost
java.rmi.server.randomIDs=true
sun.io.unicode.encoding=UnicodeLittle
java.class.version=59.0
---- Command Line ---
Empty
---- Full Classpath ---
Empty
---- Compiler Messages ---
Empty
